{
  "contas": [
    {
      "id": 1,
      "id_cliente": 1,
      "gerenteId": 3,
      "saldo": 288.50000000000006,
      "limite": 1000
    },
    {
      "id": 2,
      "id_cliente": 2,
      "gerenteId": 1,
      "saldo": 1000,
      "limite": 0
    },
    {
      "id": 3,
      "id_cliente": 3,
      "gerenteId": 3,
      "saldo": 100,
      "limite": 1000
    },
    {
      "id": 4,
      "id_cliente": 4,
      "gerenteId": 3,
      "saldo": -1000,
      "limite": 1000
    },
    {
      "id": 5,
      "id_cliente": 5,
      "gerenteId": 3,
      "saldo": -5000,
      "limite": 1000
    }
  ],
  "movimentacoes": [
    {
      "dataHora": "2023-09-01T22:00:34.133Z",
      "type": "DEPOSITO",
      "value": 1,
      "conta_id": 1,
      "conta_destiny": null,
      "id": 1
    },
    {
      "dataHora": "2023-09-01T22:00:54.775Z",
      "type": "DEPOSITO",
      "value": 12,
      "conta_id": 1,
      "conta_destiny": null,
      "id": 2
    },
    {
      "dataHora": "2023-09-01T22:16:47.368Z",
      "type": "DEPOSITO",
      "value": 1.05,
      "conta_id": 2,
      "conta_destiny": null,
      "id": 3
    },
    {
      "dataHora": "2023-09-01T22:16:47.368Z",
      "type": "DEPOSITO",
      "value": 1.5,
      "conta_id": 1,
      "conta_destiny": null,
      "id": 4
    },
    {
      "dataHora": "2023-09-01T22:26:43.553Z",
      "type": "DEPOSITO",
      "value": 1,
      "conta_id": 1,
      "conta_destiny": null,
      "id": 5
    },
    {
      "dataHora": "2023-09-01T22:27:45.557Z",
      "type": "DEPOSITO",
      "value": 1,
      "conta_id": 1,
      "conta_destiny": null,
      "id": 6
    },
    {
      "dataHora": "2023-09-01T22:27:54.641Z",
      "type": "DEPOSITO",
      "value": 2,
      "conta_id": 1,
      "conta_destiny": null,
      "id": 7
    },
    {
      "dataHora": "2023-09-01T22:28:25.857Z",
      "type": "DEPOSITO",
      "value": 2,
      "conta_id": 1,
      "conta_destiny": null,
      "id": 8
    },
    {
      "dataHora": "2023-09-01T22:28:35.555Z",
      "type": "DEPOSITO",
      "value": 2,
      "conta_id": 1,
      "conta_destiny": null,
      "id": 9
    },
    {
      "dataHora": "2023-09-01T22:29:01.779Z",
      "type": "DEPOSITO",
      "value": 100,
      "conta_id": 1,
      "conta_destiny": null,
      "id": 10
    },
    {
      "dataHora": "2023-09-01T22:29:19.739Z",
      "type": "DEPOSITO",
      "value": 0.22,
      "conta_id": 1,
      "conta_destiny": null,
      "id": 11
    },
    {
      "dataHora": "2023-09-01T22:30:51.301Z",
      "type": "DEPOSITO",
      "value": 10.23,
      "conta_id": 1,
      "conta_destiny": null,
      "id": 12
    },
    {
      "dataHora": "2023-09-07T07:33:46.690Z",
      "type": "SAQUE",
      "value": 15,
      "conta_id": 1,
      "conta_destiny": null,
      "contaId": "1",
      "id": 13
    }
  ],
  "auth": [
    {
      "id": 1,
      "nome": "cleitin",
      "email": "cliente@cliente.com",
      "senha": "1234",
      "type": "CLIENTE"
    },
    {
      "id": 2,
      "nome": "joao",
      "email": "cliente2@cliente.com",
      "senha": "1234",
      "type": "CLIENTE"
    },
    {
      "id": 3,
      "nome": "ademir",
      "email": "admin@admin",
      "senha": "admin",
      "type": "ADMIN"
    }
  ],
  "clientes": [
    {
      "id": 1,
      "nome": "cleitin",
      "email": "cliente@cliente.com",
      "cpf": "72726892183",
      "endereco": {
        "tipo": "Avenida",
        "logradouro": "Principal",
        "numero": "1234",
        "complemento": "casebre",
        "cep": "81280340",
        "cidade": "Cidade c",
        "estado": "Parana"
      },
      "telefone": "51222222222",
      "salario": 4500,
      "situacao": "APROVADO"
    },
    {
      "id": 2,
      "nome": "joao",
      "email": "cliente2@cliente.com",
      "cpf": "03214864807",
      "endereco": {
        "tipo": "Rua",
        "logradouro": "Secundaria",
        "numero": "450",
        "complemento": "casa",
        "cep": "82280380",
        "cidade": "Cidade B",
        "estado": "Parana"
      },
      "telefone": "41999123456",
      "salario": 3000,
      "situacao": "APROVADO"
    },
    {
      "id": 3,
      "nome": "teste",
      "email": "teste@gmail.com",
      "cpf": "09161477974",
      "endereco": {
        "tipo": "Rua",
        "logradouro": "Frederico Carlos Bobbins",
        "numero": "111",
        "complemento": "casa",
        "cep": "81240530",
        "cidade": "Curitiba",
        "estado": "PR"
      },
      "telefone": "44444444444",
      "salario": 5000,
      "situacao": "PENDENTE"
    },
    {
      "id": 4,
      "nome": "teste2",
      "email": "teste2@gmail.com",
      "cpf": "38185469598",
      "endereco": {
        "tipo": "Rua",
        "logradouro": "Lello Marchine",
        "numero": "500",
        "complemento": "prédio",
        "cep": "81240420",
        "cidade": "Curitiba",
        "estado": "PR"
      },
      "telefone": "44444444444",
      "salario": 50000,
      "situacao": "PENDENTE"
    }
  ],
  "gerentes": [
    {
      "id": 1,
      "nome": "gerente1",
      "email": "gerente@gerente",
      "telefone": "41999180417"
    },
    {
      "id": 3,
      "nome": "gerente3",
      "email": "gerente@gerente",
      "telefone": "41999180417"
    }
  ]
}